AUTHORS
CHANGELOG
LICENSE
MANIFEST.in
README.rst
setup.py
phil/__init__.py
phil/_version.py
phil/check.py
phil/cmdline.py
phil/util.py
phil.egg-info/PKG-INFO
phil.egg-info/SOURCES.txt
phil.egg-info/dependency_links.txt
phil.egg-info/requires.txt
phil.egg-info/top_level.txt
phil.egg-info/zip-safe
phil/tests/__init__.py
phil/tests/test_check.py
phil/tests/test_utils.py
scripts/phil-cmd