Metadata-Version: 1.1
Name: phil
Version: 1.3
Summary: Sends email reminders for events in an iCalendar file
Home-page: http://github.com/willkg/phil
Author: Will Kahn-Greene
Author-email: willg@bluesock.org
License: GPL
Keywords: phil icalendar rrule email
Platform: UNKNOWN
Classifier: Development Status :: 5 - Production/Stable
Classifier: Environment :: Console
Classifier: License :: OSI Approved :: GNU General Public License (GPL)
Classifier: Operating System :: POSIX :: Linux
Classifier: Topic :: Communications :: Email
Classifier: Programming Language :: Python
Classifier: Programming Language :: Python :: 2.6
Classifier: Programming Language :: Python :: 2.7
